ab_decrypt/__init__.py
ab_decrypt/cli.py
ab_decrypt/decryptor.py
ab_decrypt-1.0.0.dist-info/entry_points.txt
ab_decrypt-1.0.0.dist-info/LICENSE
ab_decrypt-1.0.0.dist-info/WHEEL
ab_decrypt-1.0.0.dist-info/METADATA
ab_decrypt-1.0.0.dist-info/RECORD
